{"card_name": "Spritestenosix", "color": "B", "rarity": "common", "type": "Creature \u2013 Faerie Vampire", "number": 121, "color_identity": "WUB", "cost": "{3}{B}", "rules_text": "As long as a player has discarded a card this turn, this creature has lifelink.\n{WU}{WU}, or pay 4 life: This creature gains flying until end of turn.", "pt": "3/3", "special_text": "", "shape": "normal", "set": "skp", "loyalty": "", "notes": "https://x.com/KamikiriRIP/status/1803477713577189736/photo/1\n\nOG Art_1:\nhttps://twitter.com/Kamikiri_T/status/1430845872753971200/photo/1\n\n\n\nOG: Flying\nHeroic \u2014 Whenever you cast a spell that targets CARDNAME, it gets +2/+0 until end of turn and you lose 1 life."}