{"card_name": "Prechronal Undergrowth", "color": "", "rarity": "uncommon", "type": "Land", "number": 249, "color_identity": "BRG", "cost": "", "rules_text": "Prechronal Undergrowth enters the battlefield tapped unless you\u2019ve cast an instant or sorcery spell this turn.\n{T}, Add {B}, {R}, or {G}.", "pt": "", "special_text": "", "shape": "normal", "set": "skp", "loyalty": "", "notes": "https://www.artstation.com/artwork/vJ5d46\n\n\nOG art_1:\n@exphrasis on Twitter\nhttps://twitter.com/exphrasis/status/1448370550665986049/photo/1"}