{"card_name": "Wredger", "color": "B", "rarity": "uncommon", "type": "Artifact Creature \u2013 Construct", "number": 115, "color_identity": "B", "cost": "{2}{B}", "rules_text": "Whenever this creature blocks, discard a card.\n{3}{B}, Mill two cards: Return this creature from your graveyard to the battlefield. Activate only as a sorcery. This ability costs {2} less to activate if you control three or more artifact creatures.", "pt": "4/3", "special_text": "", "shape": "normal", "set": "JDK", "loyalty": "", "notes": "https://www.artstation.com/artwork/28V3me\n\n\n\nOG_2:\nAA costed 4B, and cost reduction was 3 mana.\n\n\n\n\nOG_1:\nWhenever MV3 Wredger blocks, discard a card.\n1B, Mill two cards: Return MV3 Wredger from your graveyard to the battlefield. Activate only as a sorcery and only if you control three or more artifact creatures."}