{"card_name": "Heiromancer Hologram", "color": "W", "rarity": "common", "type": "Creature \u2013 Cleric Illusion", "number": 12, "color_identity": "W", "cost": "{2}{W}", "rules_text": "When this creature enters, draw a card. Then if you don\u2019t control a modified creature, put a card from your hand on the bottom of your library.", "pt": "3/2", "special_text": "", "shape": "normal", "set": "JDK", "loyalty": "", "notes": "http://joelchaimholtzman.com/cyberpapacy.html\n\n\nOG art_1:\niingezo on tumblr\nhttps://www.tumblr.com/iingezo/723229915505426432/mansur-amat-for-nekomomoz?source=share\n\n\nOG_1:\n3W\nAffinity for artifacts. (This spell costs 1 less to cast for each artifact you control.)\nWhen CARDNAME enters the battlefield, draw a card\n3/2"}