{"card_name": "The Goldigarch", "color": "", "rarity": "rare", "type": "Legendary Artifact \u2013 Vehicle", "number": 244, "color_identity": "C", "cost": "{4}", "rules_text": "Flying\nWhenever The Goldigarch attacks, put two +1/+1 counters on each artifact creature, vehicle, and implant you control.\nCrew 3", "pt": "3/3", "special_text": "", "shape": "normal", "set": "JDK", "loyalty": "", "notes": "https://www.deviantart.com/jessada-art/art/Golden-Ship-171778584\n\n\n\nOG_1:\nWasn\u2019t legendary"}