{"card_name": "Brightlash Mothguard", "color": "W", "rarity": "rare", "type": "Creature \u2013 Insect Soldier", "number": 4, "color_identity": "W", "cost": "{2}{W}", "rules_text": "[i]Proficiency[/i] \u2013 Whenever this creature becomes a target of an activated ability you control, return target nonland permanent card with mana value 2 or less from your graveyard to the battlefield with a finality counter. Each ability source triggers this only once each turn.", "pt": "3/2", "special_text": "", "shape": "normal", "set": "JDK", "loyalty": "", "notes": "https://www.artstation.com/artwork/BAQq9\n\n\nOG_1:\nProficiency \u2014 Whenever you activate an ability targeting this creature, you gain 2 life. Each ability source triggers this only once each turn.\n\n\n"}