{"card_name": "Metalmancer", "color": "U", "rarity": "uncommon", "type": "Creature \u2013 Dwarf Artificer", "number": 66, "color_identity": "U", "cost": "{4}{U}{U}", "rules_text": "Vigilance\n{T}, Return an artifact you own to your hand: Put an artifact card artifact card with mana value equal to 1 plus the returned artifact\u2019s mana value from your hand onto the battlefield.", "pt": "5/6", "special_text": "", "shape": "normal", "set": "JDK", "loyalty": "", "notes": "https://www.deviantart.com/gegig/art/Resurrector-500247223\n\n\n\nog_1:\nThis creature\u2019s power is equal to the greatest mana value among artifacts or equipped creatures you control."}